nltokeniz/__init__.py
nltokeniz/__main__.py
nltokeniz/tokeniz.py
nltokeniz-0.0.5.dist-info/DESCRIPTION.rst
nltokeniz-0.0.5.dist-info/METADATA
nltokeniz-0.0.5.dist-info/RECORD
nltokeniz-0.0.5.dist-info/WHEEL
nltokeniz-0.0.5.dist-info/entry_points.txt
nltokeniz-0.0.5.dist-info/metadata.json
nltokeniz-0.0.5.dist-info/top_level.txt
